{
    "gallery": [
        { "image": "./Jodhpur-1.jpg", "title": "" },
        { "image": "./Jodhpur-2.jpg", "title": "" },
        { "image": "./Jodhpur-3.jpg", "title": "" },
        { "image": "./Jodhpur-4.jpg", "title": "" },
        { "image": "./Jodhpur-5.jpg", "title": "" },
        { "image": "./Jodhpur-6.jpg", "title": "" },
        { "image": "./Jodhpur-7.jpg", "title": "" },
        { "image": "./Jodhpur-8.jpg", "title": "" },
        { "image": "./Jodhpur-9.jpg", "title": "" },
        { "image": "./Jodhpur-10.jpg", "title": "" },
        { "image": "./Jodhpur-11.jpg", "title": "" },
        { "image": "./Jodhpur-12.jpg", "title": "" },
        { "image": "./Jodhpur-13.jpg", "title": "" },
        { "image": "./Jodhpur-14.jpg", "title": "" }
    ]
}
